ntfy_webpush.py
ntfy_webpush-0.1.3.dist-info/METADATA
ntfy_webpush-0.1.3.dist-info/RECORD
ntfy_webpush-0.1.3.dist-info/WHEEL
ntfy_webpush-0.1.3.dist-info/entry_points.txt
ntfy_webpush-0.1.3.dist-info/top_level.txt
